odoo/addons/account_analytic_organization/README.rst
odoo/addons/account_analytic_organization/__init__.py
odoo/addons/account_analytic_organization/__manifest__.py
odoo/addons/account_analytic_organization/i18n/account_analytic_organization.pot
odoo/addons/account_analytic_organization/i18n/ca.po
odoo/addons/account_analytic_organization/i18n/es.po
odoo/addons/account_analytic_organization/i18n/it.po
odoo/addons/account_analytic_organization/models/__init__.py
odoo/addons/account_analytic_organization/models/account_analytic_line.py
odoo/addons/account_analytic_organization/models/account_analytic_organization.py
odoo/addons/account_analytic_organization/models/account_move_line.py
odoo/addons/account_analytic_organization/models/res_partner.py
odoo/addons/account_analytic_organization/readme/CONTRIBUTORS.md
odoo/addons/account_analytic_organization/readme/DESCRIPTION.md
odoo/addons/account_analytic_organization/readme/USAGE.md
odoo/addons/account_analytic_organization/security/ir.model.access.csv
odoo/addons/account_analytic_organization/static/description/icon.png
odoo/addons/account_analytic_organization/static/description/index.html
odoo/addons/account_analytic_organization/views/account_analytic_line.xml
odoo/addons/account_analytic_organization/views/account_analytic_organization.xml
odoo/addons/account_analytic_organization/views/account_move_line.xml
odoo/addons/account_analytic_organization/views/res_partner.xml
odoo_addon_account_analytic_organization-17.0.1.0.0.3.dist-info/METADATA
odoo_addon_account_analytic_organization-17.0.1.0.0.3.dist-info/WHEEL
odoo_addon_account_analytic_organization-17.0.1.0.0.3.dist-info/top_level.txt
odoo_addon_account_analytic_organization-17.0.1.0.0.3.dist-info/RECORD
