Metadata-Version: 2.1
Name: odoo-addon-account_analytic_organization
Version: 17.0.1.0.0.3
Requires-Python: >=3.10
Requires-Dist: odoo>=17.0a,<17.1dev
Summary: Adds organization field on the partner so you can use it on your analytic
Home-page: https://github.com/OCA/account-analytic
License: AGPL-3
Author: Miquel Pascual, Bernat Obrador, Odoo Community Association (OCA)
Author-email: support@odoo-community.org
Classifier: Programming Language :: Python
Classifier: Framework :: Odoo
Classifier: Framework :: Odoo :: 17.0
Classifier: License :: OSI Approved :: GNU Affero General Public License v3
